auto_refresh_build_pages/__init__.py
auto_refresh_build_pages/plugin.py
auto_refresh_build_pages/js/auto_refresh_build_pages.js.jinja
mkdocs_auto_refresh_build_pages-1.0.3.dist-info/licenses/LICENSE
mkdocs_auto_refresh_build_pages-1.0.3.dist-info/METADATA
mkdocs_auto_refresh_build_pages-1.0.3.dist-info/WHEEL
mkdocs_auto_refresh_build_pages-1.0.3.dist-info/entry_points.txt
mkdocs_auto_refresh_build_pages-1.0.3.dist-info/top_level.txt
mkdocs_auto_refresh_build_pages-1.0.3.dist-info/RECORD
