Metadata-Version: 2.4
Name: mkdocs-auto-refresh-build-pages
Version: 1.0.3
Summary: MkDocs plugin that automatically refreshes the build pages when the page has been rebuilt.
Home-page: https://github.com/JakubAndrysek/mkdocs-auto-refresh-build-pages
Author: Jakub Andrýsek
Author-email: email@kubaandrysek.cz
License: MIT
Keywords: mkdocs plugin,mkdocs,auto refresh,auto refresh build pages
Classifier: License :: OSI Approved :: MIT License
Classifier: Programming Language :: Python :: 3.7
Classifier: Programming Language :: Python :: 3.8
Classifier: Programming Language :: Python :: 3.9
Classifier: Programming Language :: Python :: 3.10
Classifier: Programming Language :: Python :: 3.11
Classifier: Programming Language :: Python :: 3.12
Classifier: Operating System :: OS Independent
Requires-Python: >=3.7
License-File: LICENSE
Requires-Dist: mkdocs~=1.6.0
Provides-Extra: dev
Requires-Dist: mkdocs-material~=9.5.27; extra == "dev"
Requires-Dist: mkdocs-glightbox~=0.4.0; extra == "dev"
Requires-Dist: mkdocs-git-revision-date-localized-plugin~=1.2.6; extra == "dev"
Requires-Dist: mkdocs-open-in-new-tab; extra == "dev"
Requires-Dist: build; extra == "dev"
Requires-Dist: twine; extra == "dev"
Requires-Dist: setuptools~=70.0.0; extra == "dev"
Dynamic: author
Dynamic: author-email
Dynamic: classifier
Dynamic: description
Dynamic: description-content-type
Dynamic: home-page
Dynamic: keywords
Dynamic: license
Dynamic: license-file
Dynamic: provides-extra
Dynamic: requires-dist
Dynamic: requires-python
Dynamic: summary
